lightweight/__init__.py
lightweight/cli.py
lightweight/errors.py
lightweight/files.py
lightweight/included.py
lightweight/lw.py
lightweight/py.typed
lightweight/server.py
lightweight/site.py
lightweight/templates.py
lightweight/content/__init__.py
lightweight/content/content_abc.py
lightweight/content/copies.py
lightweight/content/jinja_page.py
lightweight/content/lwmd.py
lightweight/content/md_page.py
lightweight/content/sass_scss.py
lightweight/generation/__init__.py
lightweight/generation/context.py
lightweight/generation/path.py
lightweight/generation/task.py
lightweight/project-template/blog.html
lightweight/project-template/index.html
lightweight/project-template/labs.html
lightweight/project-template/requirements.txt.j2
lightweight/project-template/website.py.j2
lightweight/project-template/_templates_/base.html
lightweight/project-template/_templates_/blog/post.html
lightweight/project-template/img/icons/android-icon-144x144.png
lightweight/project-template/img/icons/android-icon-192x192.png
lightweight/project-template/img/icons/android-icon-36x36.png
lightweight/project-template/img/icons/android-icon-48x48.png
lightweight/project-template/img/icons/android-icon-72x72.png
lightweight/project-template/img/icons/android-icon-96x96.png
lightweight/project-template/img/icons/apple-icon-114x114.png
lightweight/project-template/img/icons/apple-icon-120x120.png
lightweight/project-template/img/icons/apple-icon-144x144.png
lightweight/project-template/img/icons/apple-icon-152x152.png
lightweight/project-template/img/icons/apple-icon-180x180.png
lightweight/project-template/img/icons/apple-icon-57x57.png
lightweight/project-template/img/icons/apple-icon-60x60.png
lightweight/project-template/img/icons/apple-icon-72x72.png
lightweight/project-template/img/icons/apple-icon-76x76.png
lightweight/project-template/img/icons/apple-icon-precomposed.png
lightweight/project-template/img/icons/apple-icon.png
lightweight/project-template/img/icons/favicon-16x16.png
lightweight-1.0.0.dev53.dist-info/LICENSE
lightweight-1.0.0.dev53.dist-info/METADATA
lightweight-1.0.0.dev53.dist-info/WHEEL
lightweight-1.0.0.dev53.dist-info/entry_points.txt
lightweight-1.0.0.dev53.dist-info/top_level.txt
lightweight-1.0.0.dev53.dist-info/RECORD
