Metadata-Version: 2.1
Name: lightweight
Version: 1.0.0.dev53
Summary: Code over configuration static site generator.
Home-page: https://github.com/mdrachuk/lightweight
Author: mdrachuk
Author-email: misha@drach.uk
License: MIT
Project-URL: Pipelines, https://dev.azure.com/misha-drachuk/lightweight
Project-URL: Source, https://github.com/mdrachuk/lightweight/
Project-URL: Issues, https://github.com/mdrachuk/lightweight/issues
Keywords: static-site-generator
Classifier: Intended Audience :: Developers
Classifier: Topic :: Utilities
Classifier: Development Status :: 3 - Alpha
Classifier: License :: OSI Approved :: MIT License
Classifier: Natural Language :: English
Classifier: Operating System :: MacOS :: MacOS X
Classifier: Operating System :: POSIX
Classifier: Operating System :: POSIX :: BSD
Classifier: Operating System :: POSIX :: Linux
Classifier: Operating System :: Microsoft :: Windows
Classifier: Programming Language :: Python
Classifier: Programming Language :: Python :: 3.10
Classifier: Programming Language :: Python :: Implementation :: CPython
Classifier: Typing :: Typed
Requires-Python: >=3.10
License-File: LICENSE
Requires-Dist: Jinja2 ==3.1.2
Requires-Dist: libsass ==0.22.0
Requires-Dist: MarkupSafe ==2.0.1
Requires-Dist: python-frontmatter ~=0.4.5
Requires-Dist: python-slugify ~=3.0.3
Requires-Dist: mistune ==0.8.4
Requires-Dist: watchgod ==0.8.2
